{
  "name": "Parse CSV",
  "version": "0.0.1",
  "ref": "github.com/mellistibco/flogo-activities/activities/parsecsv",
  "type": "flogo:activity",
  "title": "ParseCSV",
  "description": "Parse CSV into a Flogo Array",
  "author": "Matt Ellis <mellis@tibco.com>",
  "inputs":[
    {
      "name": "fieldNames",
      "type": "array",
      "required": true
    },
    {
      "name": "csv",
      "type": "string",
      "required": false
    },
    {
      "name": "file",
      "type": "string",
      "required": false
    }
  ],
  "outputs": [
    {
      "name": "output",
      "type": "array"
    }
  ]
}
